drumsd.py
setup.cfg
setup.py
drums/__init__.py
drums/_common.py
drums/_host.py
drums/_latency.py
drums/_ping.py
drums/_process.py
drums/_sock.py
drums_daemon.egg-info/PKG-INFO
drums_daemon.egg-info/SOURCES.txt
drums_daemon.egg-info/dependency_links.txt
drums_daemon.egg-info/requires.txt
drums_daemon.egg-info/top_level.txt
test/test_drums.py
test/test_drumsd.py