Metadata-Version: 1.1
Name: drums-daemon
Version: 0.9.1
Summary: drums is a system monitoring tool. It provides an easy to use async API to register system monitoring tasks.
Home-page: http://autonomylab.org/drums/
Author: Mani Monajjemi
Author-email: mmonajje@sfu.ca
License: Apache License 2.0
Download-URL: https://github.com/drums-project/drums-daemon/tarball/0.9.1
Platform: UNKNOWN
